cheezokdi10.py
cheezokdi10-0.1.dist-info/METADATA
cheezokdi10-0.1.dist-info/WHEEL
cheezokdi10-0.1.dist-info/top_level.txt
cheezokdi10-0.1.dist-info/RECORD
